{
  "package": "@octokit/rest",
  "audits": [
    {
      "date": "2026-04-02",
      "scan_file": "scan-octokit-rest-2026-04-02.json",
      "repos_scanned": 17,
      "repos_affected": 1,
      "affect_rate": 0.06,
      "total_violations": 1,
      "violations_by_function": {
        "get": {
          "violation_count": 1,
          "repo_count": 1,
          "repos": ["birobirobiro/awesome-shadcn-ui"]
        }
      },
      "contract_changes": [
        "Updated last_verified to 2026-04-02",
        "Updated evidence_quality from stub to confirmed (0% FP rate)",
        "Added evidence comment blocks to all postconditions with scan data"
      ],
      "scanner_changes": [],
      "false_positive_check": {
        "repos_tested": 101,
        "type_a_fps": 0,
        "fp_rate": 0.0
      }
    }
  ]
}
